{
  "subject": "Civic Education",
  "subjectSlug": "civic-education",
  "form": 1,
  "formFromFilename": null,
  "term": null,
  "sourceFile": "CIVIC_EDUCATION_TEACHING_MODULE-PDF.pdf",
  "md5": "8087fe7d4f4c30fcd9b3b09505fe38ac",
  "detectedShift": 0,
  "pageCount": 51,
  "coverageNote": "Form directories exist only where teaching-module source PDFs were ingested. Missing forms must resolve as known-gap, not empty objects.",
  "kind": "subject",
  "topicSlug": "outline-the-social-economic-political-cultural-and-environme",
  "lesson": {
    "week": 3,
    "lesson": 3,
    "title": "Outline the social, economic, political, cultural and environmental benefits of Civic Education.",
    "topics": [],
    "activities": [],
    "resources": [],
    "assessment": [],
    "notes": ""
  }
}
