{
  "subject": "Civic Education",
  "subjectSlug": "civic-education",
  "form": 1,
  "formFromFilename": null,
  "term": null,
  "sourceFile": "CIVIC_EDUCATION_TEACHING_MODULE-PDF.pdf",
  "md5": "8087fe7d4f4c30fcd9b3b09505fe38ac",
  "detectedShift": 0,
  "pageCount": 51,
  "coverageNote": "Form directories exist only where teaching-module source PDFs were ingested. Missing forms must resolve as known-gap, not empty objects.",
  "kind": "subject",
  "topicSlug": "state-the-values-which-civic-education-develops-in-citizens",
  "lesson": {
    "week": 4,
    "lesson": 4,
    "title": "State the values which Civic Education develops in citizens.",
    "topics": [],
    "activities": [],
    "resources": [],
    "assessment": [],
    "notes": ""
  }
}
