{
  "subject": "Lunda",
  "subjectSlug": "lunda",
  "form": 1,
  "formFromFilename": 1,
  "term": 1,
  "sourceFile": "LITERATURE-IN-LUNDA-TEACHING-MODULE-FORM-1-TERM-1.pdf",
  "md5": "c5e7d95268bf36986cd716cdc740994e",
  "detectedShift": 0,
  "pageCount": 48,
  "coverageNote": "Form directories exist only where teaching-module source PDFs were ingested. Missing forms must resolve as known-gap, not empty objects.",
  "kind": "literature",
  "topicSlug": "joshua-kasai-teacher",
  "lesson": {
    "week": 5,
    "lesson": 5,
    "title": "Joshua Kasai: Teacher,",
    "topics": ["Chifwafwa Day Secondary school, Ikelenge."],
    "activities": [],
    "resources": [],
    "assessment": [],
    "notes": ""
  }
}
