{
  "source_file": "MUSICAL-ARTS-EDUCATION-TERM-2-MODULE.pdf",
  "source_path": "Teaching Module\\MUSICAL-ARTS-EDUCATION-TERM-2-MODULE.pdf",
  "md5": "bf730864b2f0142afce9eb9e8ffe0420",
  "detected_shift": 0,
  "shift_confidence": 0.989,
  "sample_page": 19,
  "page_count": 37,
  "pages": [
    {
      "page": 1,
      "text": "MUSICAL ARTS EDUCATION \nTEACHING MODULE\nFORM 1 - TERM 2\nRepublic of Zambia\nMinistry of Education\nDeveloped by the Curriculum Development Centre\nLusaka \n2025\n\u0010\n\u0010\n"
    },
    {
      "page": 2,
      "text": "Musical Arts Education\nTeaching Module\nii\nCopyright\n© Curriculum Development Centre 2025\nAll rights reserved. No parts of this publication may be reproduced, stored in a retrieval system \nor transmitted by electronic, mechanical, photocopying, recording or other means, without the \nprior permission of the Curriculum Development Centre.\nISBN 978-9982-54-067-4\n=HP\nDEJ\u0016<EH\u0016I7B;\nFirst Published 2025 by\nZambia Educational Publishing House\nLight Industrial Area\nChishango Road\nP.O. Box 32708\nLusaka, Zambia\nPrinted by:\nZambia Educational Publishing House (ZEPH)\n"
    },
    {
      "page": 3,
      "text": "Form 1 Term 2\nTeaching Module\niii\nTable of Contents\nAuthors.......................................................................................................................................iv\nCoordinators..............................................................................................................................iv\nPreface.........................................................................................................................................v\nACKNOWLEDGEMENT........................................................................................................vi\nINTRODUCTION....................................................................................................................vii\nIcons used in the module.........................................................................................................viii\nTOPIC: 1.5 MELODY...............................................................................................................1\nSub-Topic: 1.5.1. Melodic Motion............................................................................................2\nSub Topic:1.5.2. Simple Melody Writing.................................................................................5\n1.6 TOPIC: FORM.....................................................................................................................9\n1.6.1 Sub-topic: Binary and ternary........................................................................................10\nTOPIC: 1.7 MUSICAL TERMS AND SIGNS.......................................................................13\nSub-Topic: 1.7.1 Italian Terms................................................................................................14\nSub-Topic: 1.7.2. Musical Signs.............................................................................................16\nTOPIC 1.8 HARMONY...........................................................................................................18\nSubtopic:1.8.1 Triads..............................................................................................................19\nBIBLIOGRAPHY.....................................................................................................................23\nAppendix: SAMPLE LESSON TEMPLATE.........................................................................24\nAppendix: SAMPLE LESSON PLAN....................................................................................26\n"
    },
    {
      "page": 4,
      "text": "Musical Arts Education\nTeaching Module\niv\nAuthors\nChinyama Brilliant            Subject Teacher                            Chinyongola Secondary.\nKapampa Given C.            HOD-Exp. Arts                            St. Francis Secondary-Malole   \nLuhana Tafwa                    HOD-Exp. Arts/ Examiner           Natwange Secondary\nMuyunda Adrian W.          S/Lecturer/Examiner                     Charles Lwanga College of Edu.\nSinjela Frazer   K.             S/Lecturer/Examiner                     Kitwe College of Education.\nSipalo Kaumi                    Subject Teacher                              St. John’s Secondary\nCDC also wishes to thank the following coordinators for their good leadership, commitment \nto duty and outstanding contributions\nCoordinators\nMakungu Kelvin             Curriculum Specialist  AD -CDC\nMusonda Joakim             Senior Curriculum Specialist SS-CDC\nWalima M Charles          Senior Curriculum Specialist PES-CDC\nTypesetter/Graphic Designer\nBoykin Kabulo             Graphic Designer                            Freelancer\n"
    },
    {
      "page": 5,
      "text": "Form 1 Term 2\nTeaching Module\nv\nPreface\nThe Musical Arts Education (MAE) Teaching Module for Form 1 has been developed in \nresponse to the introduction of the Competence-Based Curriculum (CBC), a transformative \ninitiative aimed at enhancing quality education and relevance.\nThis teaching module is designed to support teachers to effectively deliver Musical Arts Education \nlessons under the new curriculum. Its primary objectives are to, bridge the gap created by the \nabsence of approved textbooks and equip teachers with practical skills and assessments tailored \nto learners’ needs and levels.\nThe Ministry of Education acknowledges the challenges associated with transitioning to a new \ncurriculum. Consequently, this module reflects our commitment to providing teachers with \nstructured guidance, suggested activities, formative and summative assessments aligned with \nthe CBC’s objectives.\nWhile this module serves as a foundational resource, we encourage teachers to supplement it \nwith their own research and innovations to address potential gaps during implementation. The \nsuggested activities and assessments are designed to foster practical and critical thinking skills \nin learners, ensuring relevance and adaptability across diverse school contexts.\nTeachers are encouraged to tailor these suggestions to their unique classroom dynamics and \nexplore alternative approaches when necessary. We hope this module will empower teachers \nto navigate the new competence-based curriculum with confidence, inspiring and equipping \nlearners with applied knowledge, skills, and values.\nKelvin Mambwe (PhD)\nPermanent Secretary- Educational Services\nMINISTRY OF EDUCATION\n"
    },
    {
      "page": 6,
      "text": "Musical Arts Education\nTeaching Module\nvi\nAcknowledgement\t\nThe Musical Arts Education Teaching Module for Form 1 is the culmination of a collaborative \nand inclusive development process. I wish to extend my profound appreciation to individuals, \ninstitutions, and organisations that contributed to the module’s development, their invaluable \ninput and expertise have enriched the content and quality of this teaching module.\nI also acknowledge the dedication and hard work of the staff at the Curriculum Development \nCentre, whose tireless efforts ensured the successful completion of the teaching module \ndevelopment process.\nCharles Ndakala (Dr.)\nDirector - Curriculum Development\nMINISTRY OF EDUCATION\n"
    },
    {
      "page": 7,
      "text": "Form 1 Term 2\nTeaching Module\nvii\nIntroduction \nThe Competence-Based Curriculum (CBC) is designed to equip learners with competences \nnecessary to navigate the complexities of the modern world. This Musical Arts Education \n(MAE) teaching module is tailored to support teachers in implementing the CBC, focusing on \nthe attainment of specific competences of specified sub-topics as indicated in the syllabus, but \naligned to the general competences like creativity and innovation, critical thinking, problem-\nsolving, and effective communication.\nEach specific competence is supported by carefully designed learning activities that cater for \ndiverse learning styles and abilities. These learning activities further give guidance on how they \nshould be effectively administered to the learners to meet the expected standards that speak to the \nspecific competences. Furthermore, this module encourages teachers to assess learners’ progress \nusing a range of strategies.\nBy using this MAE teaching module, teachers will be able to support learners to acquire \ncompetences outlined in the syllabus. This will enable the development of practical skills, \nenhancement of talents, creativity, self-expression and sense of aesthetics among learners. \n"
    },
    {
      "page": 8,
      "text": "Musical Arts Education\nTeaching Module\nviii\nIcons used in the module\nSummary                          \t\nTerminology      \n     \n Assessment                 \t\n\t\nTips          \n                            \n  Activity\t \t\n\t\n\t\nDiscussion\n"
    },
    {
      "page": 9,
      "text": "Form 1 Term 2\nTeaching Module\n1\nTOPIC: 1.5 MELODY\nIntroduction \nThis topic is broken down into two subtopics which are: 1.5.1 Melodic motion and 1.5.2 Simple \nmelody writing.\nWhat is Melody?\nMelody is a fundamental element of music often considered the most memorable part of a song \nor composition. It is the backbone of music, the thread that weaves together pitches, rhythms, \nand emotions to create a rich blend of sound. It is defined as the succession of pitches heard in a \nsequence, creating a musical line or theme. \nMelody   has   practical application in various aspects of life, such as composing   jingles   and \nadvertisements to make products more memorable. It can be used in therapy, evoke emotions, \nimprove mood and aid cognitive development.\nGeneral Competences:\nLearners should acquire the following general Competences:\nAnalytical thinking: Ability to systematically examine, interpret and evaluate musical elements \nand structures, for purpose of applying them in addressing social-economical needs.\n Creativity and innovation: Ability to experiment new approaches and generate musical ideas \nthat exhibit originality   and take creative risks in the composition, performance and interpretation \nof music. \nCritical thinking: Ability to analyse, investigate and evaluate musical works, performances and \npractices with a discerning and reflective mindset to address social-economical needs.  \nCollaboration: Ability to work effectively with others in various musical setting such as \nensembles or bands and other music projects    to achieve goals in Musical Arts Education.\nCommunication: Ability to express and convey musical ideas appropriately, clearly and \neffectively (verbal and non-verbal).\n Emotional intelligence: Ability to recognise, understand, express and manage emotional stress \nin oneself and others through musical activities.\nProblem solving: Ability to use music to identify, analyse and address social-economical \nchallenges and obstacles.\nTERMINOLOGY\nAntecedent: The first part of a melodic phrase that sets up a musical idea, often ending \nin uncertainty, to be resolved by the consequent.\nConjunct motion: Smooth, stepwise movement between, consecutive pitches in\n     \t\na melody e.g. (C-D-E).\nContour: \t\nThe overall shape or pattern of ups and downs in pitch, creating a unique\n\t\noutline or topography.\nDisjunct motion: Movement between consecutive pitches in a melody by larger \nintervals, often creating a sense of leap or jump, e.g. (C-E, C-G)\nHill: \t\nThis refers to a musical phrase or section that gradually rise in pitch, often \ncreating a sense of tension, anticipation or build up.\n"
    },
    {
      "page": 10,
      "text": "Musical Arts Education\nTeaching Module\n2\n Melody: \t\nA succession of pitches in rhythm, heard in sequence, creating a musical \n      \t\n line that convey emotion, structure and character. \n Melodic devices: Techniques used by composers to create interest, variety\n       \t\nand emotional impact in a melody.\n Motif: \t\nA short, repeated pattern or idea, often just a few notes, that is used to \nbuild a melody or tune.\n Motion: \t\nThe way   pitches move in relation to each other, either smoothly (conjunct)\n\t\n\tor by   leaps (disjunct).\n Phrase: \t\nA group of notes that form a complete musical thought or idea, similar to\n         \t\na sentence in language\nValley: \t\nrefers to a musical phrase or section that descends in pitch, often creating \na sense of relaxation, resolution, or calmness.\n Wave:  \t\nA musical phrase or section that moves in a wave like motion.\nSub-Topic: 1.5.1. Melodic Motion\n Introduction \nThis subtopic focuses on two types of melodic motion, as well as identifies melodic shape. \nMelodic motion refers to the way pitches in rhythm move in relation to each other within a \nmelody, creating a sense of progression and direction. \nThere are two types of melodic motion: conjunct motion, which proceeds by step from one scale \ndegree to the next (i.e., by the interval of a 2nd), and disjunct motion, which proceeds by leap \n(i.e., by intervals larger than a 2nd)\nSpecific Competence 1.5.1 Describe the melodic motion.\nSuggested Methodology: Demonstration and individual activities …\nLearning Environment Setup: Any environment such as, (an outdoor), artificial (music room…) \nand technological (video, YouTube…) \nSuggested Teaching and Learning Materials: Piano/keyboard, guitars, visual aids such as \ncharts…\nLEARNING ACTIVITIES\n\t\n Activity 1: Identifying conjunct and disjunct motion in a melody.\nTask 1:  Learners to sing any familiar melodies (e.g. Row, row, row your boat) and \nidentify different intervals between the notes of the melody. \n"
    },
    {
      "page": 11,
      "text": "Form 1 Term 2\nTeaching Module\n3\nTIP\nEngage learners in singing different melodies and identify conjunct and disjunct motion in the \nmelodies.\nTask 2:  Play some notes like these below on the keyboard and ask learners in groups to identi­\nfy them as either conjunct or disjunct motion.\n                                         \nTIP\nDivide learners in groups and ask them to identify different notes played on the keyboard as \neither conjunct or disjunct motion.\nDISCUSSION\n \nz Learners in groups to analyse the given melodies below and identify conjunct and \ndisjunct motion. \n  \n Activity 2: Identifying the shape/contour of the melody. (valleys, waves, hill …)\n"
    },
    {
      "page": 12,
      "text": "Musical Arts Education\nTeaching Module\n4\nTask 1: Learners listen or sing simple common melodies then identify what a valley, wave or a \nhill.\nTIP\nLearners to freely explore and identify the shape/contour of different melodies with clear \nexamples of valley, waves and hills.\nExamples of a valley contour: \n \nz Twinkle, Little Star. The melody starts high, descends to a low point, and then ascends \nagain, creating a valley shape.\nWave Contour: \n \nz London Bridge is Falling Down. This traditional children’s song has a melody that \noscillates up and down creating a wave-like contour.\n \nz The Wheels on the Bus: The melody of this children’s song features a wave like \npattern, with a repetitive motion that mimics the action of the bus parts. \nHill Contour:\n \nz Happy Birthday to You: The melody starts low, rises to a high point and then descends \nslightly, forming a hill contour.\n \nz Jingle Bells: The melody starts low, ascends to high point and then remains relatively \nhigh, creating a hill shape.\nExpected Standard: Melodic motion describe correctly.\nASSESSMENT CRITERIA\n\t\n \nz Provide learners with printed melodies and ask them to identify and label they valleys, \nwaves and hills.\n \nz Give learners a melody with missing notes and ask them to complete the melody by \nadding notes that create a specific contour.\n \nz Play a series of melodies with different contours and ask learners to identify the type \nof contour used in each melody.  \n \nz Look at the following melody, taken from the popular song “This is What You Came \nFor” by Calvin Harris and Rihanna which uses a mix of conjunct and disjunct melodic \nmovement. Study the melody and then answer the questions below as a class exercise.\n"
    },
    {
      "page": 13,
      "text": "Form 1 Term 2\nTeaching Module\n5\na.\t\nIn which two bars of the song does the melody move by disjunct movement?\nb.\t\nIn which two bars of the song does the melody move by conjunct movement?\nc.\t\nWhat is the note name of the lowest pitch note in this melody? d) Identify the note \nname of the highest pitch note in this melody?\nd.\t\nMeasure the interval   between the lowest and highest note\nSUMMARY\nThis subtopic has highlighted the following:\n \nz Melodic motion refers to the movement of pitches in a melody.\n \nz There are two main types of melodic motion, and these are conjunct and disjunct \nmotion. \n \nz The overall shape or pattern of ups and downs in pitch creating a unique outline or \ntopography is referred to as a contour.\n \nz There are many types of melodic contours in music apart from valleys, waves and \nhill. \n \nz A valley refers to a musical phrase or section that descends in pitch, often creating a \nsense of relaxation, resolution, or calmness.\n \nz A wave is a musical phrase or section that moves in a wave like motion.\n \nz A hill refers to a musical phrase or section that gradually rise in pitch, often creating \na sense of tension, anticipation or build up. \nSub Topic:1.5.2. Simple Melody Writing\nIntroduction\nThe main aim of this sub-topic is to look at how to compose simple melodies using a motif, as \nan antecedent (question) and then provide the consequent (answer) with limited range of notes \nand rhythmic patterns.\nSimple melody writing refers to the process or technique of creating a short, coherent, and \nmemorable musical idea using pitch and rhythm, to convey emotion and mood.\nSpecific Competence: 1.5.2.1 Compose simple melodies.\nSuggested Methodology: Demonstration, Discussion... \nLearning Environment Setup: Any, such as natural (any outdoor environment…) artificial \n(music room…) and technological (video, online research …)\nSuggested Teaching and Learning Materials: Piano/keyboard, guitar …\nLEARNING ACTIVITIES\nActivity 1: Discussing motif in melody writing.\n"
    },
    {
      "page": 14,
      "text": "Musical Arts Education\nTeaching Module\n6\nTask 1:  Engage learners in small groups and discuss what a motif is in melody \nwriting.\nTIP\n \nPlay or sing a well-known melody that features a motif and ask learners to identify and \ndiscuss motif in the melody.\nDISCUSSION\n \nz In smaller groups learners study and identify the motifs below:\nTIP\n Highlight major features of the motif for each melody below\n \nz Learners give examples of motifs from songs of their choices.\n \nz With learners, analyse the motifs given as examples.\nActivity 2: Distinguishing various phrases in the melody (antecedent /question, consequent /\nanswer)\nTask 1: \nDISCUSSION\n"
    },
    {
      "page": 15,
      "text": "Form 1 Term 2\nTeaching Module\n7\n \nz Ask learners to discuss what a phrase is and how to distinguish it in a melody.\n \nz Learners distinguish between an antecedent /question and consequent /answer in a \ngiven melody.\nTIP\n: \nEncourage exploration among learners by asking them to distinguish between a question and an \nanswer in a melody. This can either be done in groups or individually.\n \nz Remind learners that just as they often pause between the different sections in a \nsentence (for example, when you say, “wherever you go, there you are”), a melody \nusually pauses slightly at the end of each phrase.\n \nz Emphasis should be made that in vocal music, the musical phrases tend to follow the \nphrases and sentences of the text. \nExamples of Antecedent phrases and consequent phrases\nThe melody for “Mary Had a Little Lamb” is a well -known example of a simple melody.\nThe antecedent phrase in the melody is:\n“Ma-ry had a lit-tle Lamb”\nThis phrase sets up the expectation for the consequent phrase which completes the musical \nthought:\n“Lit-tle lamb, lit-tle lamb”\nIn the melody “Mary Had a Little Lamb”, possible motif can be identified as:\n“Ma-ry had”\nThis short melodic idea (3-4 notes) is repeated and varied throughout the melody, making it a \nmotif.\nHere is a breakdown:\n \nz “Mar-ry had” (motif)\n \nz “alit-tle lamb” (variation of the motif)\n"
    },
    {
      "page": 16,
      "text": "Musical Arts Education\nTeaching Module\n8\n \nz “Lit-tle lamb, lit-tle lamb (repetition and variation of the motif)\nThis motif is then developed and expanded upon to create the complete melody.\nActivity 3: Composing Simple Melodies (At least four bars…)\nTask 1:\n \nz In smaller groups learners to compose a simple four bar melody.\nTIP\n \nz Note that when composing a melody, the following points should be considered:  \ni.\t\nTime signature and key signature,\nii.\t\nOn which scale degree and beat of the bar does the melody begin?\niii.\t\nWhat rhythmic patterns are to be used?\niv.\t\nMaintain the motif to be used in the melody, and where possible variety it. \nv.\t\nProvide a consequent to the antecedent. \nvi.\t\nSing or hum while composing the melody to internalize it. \nvii.\t\nEnd on the tonic with a long note and approach it in stepwise motion and avoid \nunnecessary wide leaps.\nExpected Standard: Simple melodies composed accordingly.\nASSESSMENT CRITERIA\n \n \nz In smaller groups, learners to complete provided melodies to ‘four’ bars by writing a \nconsequent phrase.\n \nz In pairs, learners create and vary a simple melodic motif within four bars.\n \nz Individually learners compose a ‘four’ melody in any key of their choice.\n \nz Sight sing or sight read the composed melodies\nSUMMARY\n \nz Simple melody writing (composing) refers to the process or technique of creating \na short, coherent, and memorable musical idea using pitch and rhythm, to convey \nemotion and mood.\n \nz A phrase is a unit of a musical thought that consists of a group of notes that form a \ncoherent and meaningful musical idea.\n \nz An antecedent phrase is the first phrase in a pair of phrases, typically followed by a \nconsequent phrase. \n \nz A melody is made up of phrases, which are usually two or four bars long\n \nz When composing simple melodies one should consider all necessary steps.\n \nz A motif can be, melodic or rhythmic (or it may contain a combination of the two \nelements) and is considered to be the smallest of the ‘building blocks’ – the recognis­\nable, reoccurring themes and phrases – that make up a composition\n"
    },
    {
      "page": 17,
      "text": "Form 1 Term 2\nTeaching Module\n9\n1.6 TOPIC: FORM\nIntroduction\nForm in music refers to the overall structure or organization of a piece of music. It encompasses \nthe arrangement of musical elements such as melody, harmony, rhythm, and tempo to create a \ncohesive and meaningful whole. Form is very important because it gives music a clear beginning, \nmiddle, and end, making it easier to follow and understand. Form allows composers to create \ncontrast between different sections of music, adding variety and interest. \nGeneral competence(s)\nLearners should acquire the following general competences:\nAnalytical thinking: Ability to systematically examine, interpret and evaluate musical elements \nand structures, for purpose of applying them in addressing social- economical needs.\nCritical thinking: Ability to analyse, investigate and evaluate musical works, performances and \npractices with a discerning and reflective mindset to address social-economical needs.\nCommunication: Ability to express and convey musical ideas appropriately, clearly and \neffectively (verbal and non- verbal)\nCollaboration: Ability to work effectively with others in various musical setting such as \nensembles or bands and other music projects to achieve goals in musical arts Education.\nCreativity and innovation: Ability to experiment new approaches and generate musical ideas \nthat exhibit originality   and take creative risks in the composition, performance and interpretation \nof music.\nTERMINOLOGY\nBinary Form: A simple musical structure consisting of two contrasting sections (AB)\nTernary Form: A musical structure consisting of three sections, with the first and third sections \nbeing similar (ABA)\nTheme: A recurring melody or idea\nSection: A distinct part of the music, often with its own unique characteristics\nTransition: A passage connecting two sections.\nRhythm: This is the arrangement of sounds in time, creating a sense of pulse, meter and groove.\nMelody: Is a succession of pitches heard in sequence, creating a musical line.\nSequence: A repetition pattern of pitches at a higher or lower level.\nRepetition: Repeating a melodic idea or pattern\nVariation: Changing a melodic idea or pattern while maintaining its core identity. \n"
    },
    {
      "page": 18,
      "text": "Musical Arts Education\nTeaching Module\n10\n1.6.1 Sub-topic: Binary and ternary\nIntroduction\nBinary form is one of the simplest and most common musical forms, used in a wide range of \nmusical styles and genres. It is a fundamental concept in music theory, and understanding binary \nform helps one analyse and appreciate the structure of many musical compositions. Binary form \nconsists of two contrasting sections, often labeled as A and B. The A section typically presents a \ntheme or melody, while the B section presents a contrasting theme or develops the initial theme. \nThe two sections are usually of equal or approximately equal length.\nTernary form on the other hand, is a musical structure consisting of three main sections, typically \nrepresented as A-B-A. This means the piece begins with an initial theme or section (A), followed \nby a contrasting middle section (B), and concludes with a return to the initial theme or section \n(A). Ternary form provides a sense of balance and symmetry, making it a popular choice for \ncomposers and songwriters.\nExample of Binary form\nTernary Form ABA\nSpecific competence: 1.6.1.1 Construct melody in binary and ternary forms\nSuggested Methodology: Demonstration, group and individual activities…\n"
    },
    {
      "page": 19,
      "text": "Form 1 Term 2\nTeaching Module\n11\nLEARNING ACTIVITIES\nLearning environment setup: You can teach the learners from any of the \nenvironments such as natural (any outdoor environment…), artificial (music room…) \nand technological (video…)\nSuggested Teaching and Learning Materials: Piano/Keyboard, blue tooth speaker, \nprojectors, and visual aids such as charts…\nActivity 1: Detecting rhythmic and melodic contrast\nTask 1: Ask learners to listen, sing or play simple melodies like “Baba Black sheep” \nand identify rhythmic and melodic contrast.  \nTIP\nPromote analytical thinking by allowing learners to listen, sing or play simple \nmelodies and identify rhythmic and melodic contrast.  \nTask 2: Play a melody with a contrasting contour or rhythm and ask learners to \nimitate it. Then, ask them to create their own melody.\nTIP\nEncourage creativity among the learners by asking them to create their own melody \nwith a contrasting contour. This can either be written or performed (singing or \ninstrument playing) \nTask 3: Provide learners with a score or recording a piece. Ask them to analyse the \nform, identifying areas of contrast and unity. \nTIP\nProvide each learner with a score and then allow them to analyse the form of the giv­\nen song identifying areas of contrast and unity.\nActivity 2: Constructing sections of equal length of binary and ternary structure\nTask 1: Ask learners to compose a short piece in binary or ternary form ensuring each \nsection A and B or A, B and A have the equal number of measures (4 measures each)\nTIP\nPut learners in groups so that they work as a team and later on allow them to do the \nwork individually. Encourage critical thinking and creativity as they work on this \nactivity.\nTask 2: Class discussion on the characteristics of binary and ternary forms. Ask \nlearners to share their compositions and provide feedback on section length and \ncontrast.\n"
    },
    {
      "page": 20,
      "text": "Musical Arts Education\nTeaching Module\n12\nTIP\nFacilitate a class discussion on the characteristics of binary and ternary forms. Ensure \nthat each learner is fully involved in the discussion.\nActivity 3: Constructing sections of unequal length in binary and ternary design.\nTask 1: Ask learners to compose a binary form piece(AB) with sections of unequal \nlength (e.g., 4 measures in A and 6 measures in B) or Ask them to compose a ternary \nform piece (ABA) with sections of unequal length (e.g., 4 measures in A, 6 measures \nin B and 4 measures in A.\nTIP\nEnsure that the constructed measures are not equal. \nTask 2: Provide learners with a partially completed binary or ternary form piece. \nAsk them to expand one section (e.g., add 4 measures to section A in binary form) or \nexpand the middle section (B) in ternary form while maintaining the outer sections’ \nlength. \nTIP\nEnsure that the suggested sections for binary and ternary forms are expanded as ex­\npected.\nTask 3: Give learners a score in binary or ternary form with unequal length. Ask them \nto identify and label the sections.\nTIP\nEnsure that leaners are able to identify and label the sections. Guide the learners \nthroughout the lesson.\nExpected standard: Melodies in binary and ternary form constructed correctly\nASSESSMENT CRITERIA\nPrepare tasks to be administered during and after learning sessions and give carry \nhome tasks.\n \nz Form and analysis – Analyse and identify the form of provided melodies \n \nz Written and practical assessment (composing and performing melodies in binary or \nternary form).\nSUMMARY\n This topic has highlighted the following:\n \nz Musical form refers to the overall structure or organization of a piece of music.\n \nz Binary is a simple musical structure with two sections while ternary is a simple mu­\nsical structure with three sections.\n \nz Form is shaped by theme, section, transition, development and repetition.\n"
    },
    {
      "page": 21,
      "text": "Form 1 Term 2\nTeaching Module\n13\nTOPIC: 1.7 MUSICAL TERMS AND SIGNS\nIntroduction \nMusical terms and signs are specialized words and symbols used in music notation to convey \ninformation about pitch, rhythm, dynamics, articulation, and other aspects of musical performance. \nMusical terms and signs are important in that they help musicians read music fluently, play \nexpressively and perform pieces accurately.\nThere are so many musical terms and signs used in music, as such this topic will not cover all \nof them. This topic is broken down into two subtopics which are: Italian terms that deal with \ninterpreting tempo and dynamics.\nGeneral Competences:\nLearners should acquire the following general Competences:\nAnalytical thinking: Ability to systematically examine, interpret and evaluate musical elements \nand structures, for purpose of applying them in addressing social-economical needs.\n Creativity and innovation: Ability to experiment new approaches and generate musical ideas \nthat exhibit originality   and take creative risks in the composition, performance and interpretation \nof music. \nCritical thinking: Ability to analyse, investigate and evaluate musical works, performances and \npractices with a discerning and reflective mindset to address social-economical needs.  \nCollaboration: Ability to work effectively with others in various musical setting such as \nensembles or bands and other music projects    to achieve goals in Musical Arts Education.\nCommunication: Ability to express and convey musical ideas appropriately, clearly and \neffectively (verbal and non-verbal).\n Emotional intelligence: Ability to recognise, understand, express and manage emotional stress \nin oneself and others through musical activities.\nProblem solving: Ability to use music to identify, analyse and address social-economic \nchallenges and obstacles.\nTERMINOLOGY\nBelow are some of the terminologies Interpreting the Italian terms for tempo:\nAccelerando (accel.): Getting quicker\nAdagio: Leisurely – usually quite slow\nAdagietto: Slow, gentle tempo\nAllegretto: Moderate, playful tempo\nAllegro: (cheerful) fast\nAndante: (easy going) At a walking pace\n"
    },
    {
      "page": 22,
      "text": "Musical Arts Education\nTeaching Module\n14\nAndantino: Not as slow as andante\nA tempo: Returning to the original tempo after a deviation\nGrave: Usually very slow\nLarghetto: Slow, lyrical tempo, rather broadly\nLargo: Very slow, dignified tempo\nLento: Slow tempo, slower than largo\nModerato: Moderate tempo (moderately)\nPresto: Very fast\nRitardando: (rit) holding back\nScherzo:  Fast, lively\nVivace: Full of life, fast, lively tempo.\nSub-Topic: 1.7.1 Italian Terms\nIntroduction \nMost musical terms are written in Italian Language because of the country’s significant \ncontributions   to the development of Western classical music. Italian composers were the first to \nwrite ‘instruction’ words at certain points in their music. Italian musical terms   have   become \nan integral part of the language of music, providing a universal vocabulary for musicians to \ncommunicate and interpret music accurately.\nThe term ‘tempo’ is derived from the Italian language. In Italian, ‘tempo’ means ‘time’ and in \nmusic, it refers to the speed or rate at which a piece of music is performed.\nSpecific Competence 1.7.1 .1. Interpret the Italian terms for tempo.\nSuggested Methodology: Demonstration, Discussion...\nLearning Environment Setup: Any environment such as, (any outdoor), artificial ( music \nroom…) and technological ( video, YouTube ) \nSuggested Teaching and Learning Materials: Piano/keyboard, guitars, visual aids such as \ncharts…\nLEARNING ACTIVITIES\n Activity 1: Interpreting the Italian terms for tempo (allegro, presto, lento …)\nTask 1: Divide learners in groups and give them a musical score sheet with Italian terms. Ask \nthem to interpret as well as demonstrate how the music will be performed. \nTIPS\n"
    },
    {
      "page": 23,
      "text": "Form 1 Term 2\nTeaching Module\n15\n \nz Engage learners to perform popular music (songs) and apply different tempo.\n \nz Learners to listen to piece of different tempo.\nExpected Standard: Italian terms for tempo interpreted correctly.\nSpecific competence: 1.7.1.2. Interpret the Italian terms for dynamics.\nActivity: 2. Interpreting the Italian terms for dynamics piano (p), forte (f)…)\nDISCUSSION\n to be done in groups.\nTask 1 Divide learners in groups and give them a musical score sheet with Italian terms for \ndynamics. Ask them to interpret as well as demonstrate how the music will be performed.\nTIP\n \nz Engage learners to interpret the Italian terms for dynamics and help them demonstrate \nhow they are applied either by singing or playing instruments as prescribed; (Soft, \nloud…)\nBelow are some of the commonly used Italian terms for dynamics:\n \nz Main dynamic markings:\n1. Pianissimo (pp): Very soft\n2. Piano (p): Soft\n3. Mezzo -piano (mp): Moderately soft\n4. Mezzo-forte (mf) moderately   loud\n5. Forte (f): Loud\n6. Fortissimo: (ff) Very loud\n \nz Gradual Dynamic Changes:\n1. Crescendo (cresc): Gradually getting louder.\n2. Decrescendo (decres: Gradually getting softer.\n3. Diminuendo (dim) getting softer.\n4. Rinforzando (rfz): Gradually getting louder and stronger\n \nz Sudden Dynamic Changes:\n1. Sforzando (sfz): Sudden, strong accent.\n2. Sforzato (sf): Sudden, strong accent (similar to sforzando).\n3. Subito: Sudden change in dynamics (e.g, subito piano for sudden softening.)\nExpected Standard: Italian terms for dynamics interpreted correctly.\nASSESSMENT CRITERIA\n"
    },
    {
      "page": 24,
      "text": "Musical Arts Education\nTeaching Module\n16\n Prepare tasks to be administered during and after learning sessions and    give carry home \ntasks.\n \nz Sight reading/singing.\n \nz Playing instruments.\n \nz Listening and analysis. \n \nz Written work.\nSUMMARY\nThis subtopic has highlighted the following:\n \nz Musical terms and signs are specialized words and symbols used in music notation to \nconvey information.\n \nz Italian composers were the first to write ‘instruction’ words to music as such Italian \nmusical terms have become an integral part of the language of music.\n \nz Tempo refers to the speed or rate at which a piece of music is performed.\n \nz In music, dynamics refer to the varying degrees of loudness and softness in a musical \ncomposition. It describes the contrast between quiet and loud sounds, which adds \nexpression, emotion, and depth to the music. By varying dynamics, musicians add \nfeeling to their performance, making music engaging and impactful to the listener.\nSub-Topic: 1.7.2. Musical Signs\nIntroduction \nMusical signs also known as musical notation symbols, are graphical representations used to \nconvey musical information. They help musicians read and interpret musical score.\nSpecific Competence 1.7.2.1. Demonstrate musical signs in music composition\nSuggested Methodology: Demonstration, group and individual activities …\nLearning Environment Setup: Any environment    such as, (any outdoor), artificial (music \nroom…) and technological (video, YouTube) \nSuggested Teaching and Learning Materials: Piano/keyboard, guitars, visual aids such as \ncharts…\nLEARNING ACTIVITIES\n\t\nActivity 1: Identifying music signs (staccato, legato, repeat signs…)\nTask 1: Learners in groups to identify music signs (staccato, legato, repeat signs…) on a music \nscore provided like the one below.\n"
    },
    {
      "page": 25,
      "text": "Form 1 Term 2\nTeaching Module\n17\nTIPS\nGuide the learners to explore and identify music signs (staccato, legato, repeat signs…) on a \nmusic score provided.\nActivity 2: Demonstrating music signs\nTask 1: Perform melodies in groups demonstrating (staccato, legato, repeat signs…) on a music \nscore provided.\n \nTIPS\nFacilitate group performances to help learners demonstrate (staccato, legato, repeat signs…)\nExpected Standard: Musical signs demonstrated appropriately \nASSESSMENT CRITERIA\nPrepare tasks to be administered during and after learning sessions and    give carry home \ntasks.\n \nz Sight reading/singing.\n \nz Playing instruments.\n \nz Listening and analysis. \n \nz Written work (composition)\nSUMMARY\n \nz The word staccato comes from the Italian word meaning “detached” or “disconnected,” \nwhich means to play notes short and sharply, with a slight silence between each \nnote. It is indicated by a small dot (.) placed either above or below the note head, \nsignifying that the note should be played short and detached. \n \nz Legato is an Italian term meaning tied together. Legato is a performance technique \nused in music. It creates a smooth, steady flow between notes. Every single note is \nplayed to its utmost length and then harmonizes straight into the following note, \nallowing a better crescendo or decrescendo of the phrase.\n \nz In music, a repeat sign is symbol that indicate a section of music should be repeated. \n"
    },
    {
      "page": 26,
      "text": "Musical Arts Education\nTeaching Module\n18\nTOPIC 1.8 HARMONY\nIntroduction\nIn music, Harmony refers to the combination of different musical notes played or sung at the \nsame time to produce a pleasing sound. It usually supports the melody (the tune) and adds depth, \nemotion and texture to a piece of music.\nHarmony is created when two or more notes sound together, forming chords (like C major or \nG minor), or more complex structures. For instance, if someone sings or plays a melody and \nanother person sings or plays a different note that blends well with it, they are singing or playing \nin harmony. So when we think of Harmony, we are thinking of layers of sound. \nIt is a fundamental aspect of music, enhancing the emotional impact and aesthetic appeal of a \ncomposition. \nGeneral Competences:\nAnalytical thinking: Ability to systematically examine, interpret and evaluate musical elements \nand structures, for the purpose of applying them in social-economic needs.\nCollaboration: Ability to work effectively with others in various musical settings such as \nensembles or bands and other music projects to achieve goals in Musical Arts Education.\nCreativity and Innovation: Ability to experiment new approaches and generate musical ideas \nthat exhibit originality and take risks in the composition, performance and interpretation of music.\nCritical thinking: Ability to analyse, investigate and evaluate musical works, performances and \npractices with a discerning and reflective mindset to address social-economical needs.\nDigital Literacy: Ability to effectively use hardware and software to analyse, create, produce, \nand share music.\nProblem solving: Ability to use music to identify, analyse and address social-economical \nchallenges and obstacles.\nTERMINOLOGY\nCadence: A chord progression that signals the end of a phrase or section. (perfect cadence (V-I).\nChord: Is formed when two or more different notes are played or sung together. The most \ncommon is a Triad, which consists of 3 notes (C-E-G).\nChord progression:  Is a sequence of chords played in successions. (I - IV - V - I)\nConsonance: A combination of notes that sounds stable, pleasant or resolved.\nDissonance: A combination of notes that sounds tense or unstable; often used to create drama \nor resolution.\nInterval: The distance between two notes. Common intervals include 2nd, 3rd, 5th and Octaves.\nInversion: A chord where the root is not the lowest note. Changes the feel/sound of the chord.\nKey: The tonal center or home scale of a piece, which determines which chords are most \ncommonly used\nTriad: A basic three-note chord made of root, third and fifth. (D minor triad=D-F-A.)\nVoicing: Exploring different ways to arrange notes in chords can lead to fuller or more varied \nsound such as using inversions.\n"
    },
    {
      "page": 27,
      "text": "Form 1 Term 2\nTeaching Module\n19\nSubtopic:1.8.1 Triads\nIntroduction\nA triad is a three-note chord built from a root, third and fifth. It is a group of three notes played \nor sung simultaneously. \nWhen we refer to the root, third and fifth, we mean that:\n \nz The root is a base note (foundation note).\n \nz The third is a third interval above the root.\n \nz The fifth is a fifth note (a perfect 5th) above the root.\nSpecific competences: 1.8.1.1 Construct triads\nSuggested Methodology: Discussion, Demonstration, individual…\nLearning environment setup: Any environment such as, (any outdoor), artificial (music \nroom…) and technological (video…).\nSuggested Teaching and Learning Materials: Piano, keyboard, guitars, charts…\nLEARNING ACTIVITIES\n Identifying triads (Root, 3rd and 5th).\nActivity 1: Identifying triads (roots, third and fifth).\nTask 1: Ask learners to identify and label the triads as root, third and fifth on a staff using the \ntonic triad in C major.\n            \nTIP\n \nz Facilitate learners’ involvement in identifying and labelling the triads as root, third \nand fifth. \nDISCUSSION\n \nz Break learners into smaller groups to discuss and identify the triads as root, third \nand fifth.\n"
    },
    {
      "page": 28,
      "text": "Musical Arts Education\nTeaching Module\n20\nTask 2: Ask learners to either sing or play the constructed tonic triad in C major. \nTIP\nAllow learners in groups to freely explore and experiment by either singing or playing the tonic \ntriad in C major.  \nActivity 2: Constructing triads (root, 3rd, 5th)\nTask 1: Engage learners in constructing triads (root, 3rd, 5th) on the staff in different keys.\nTIP\n \nz Engage and support learners in constructing triads (root, 5th, 3rd) on either treble or \nbass staff. \nExpected standard: Triads constructed correctly.\nASSESSMENT CRITERIA\nPrepare tasks to be administered during and after learning sessions and give carry home tasks.\n \nz Identify, construct and play/sing the triads given.\n \nz Create a quiz to test learners’ ability to identify triads.\n \nz Assign a project where learners analyse and identify triads in selected score.\n \nz Give short answer questions by asking students to explain triad concepts and give \nmusical examples.\n \nz Ask learners to compose short pieces of music using triads.\nActivity 3: Describing triads (major, minor, diminished or augmented). \nTask 1: Ask learners to describe triads as (major, minor, diminished or augmented).\nTIP\n \nz Introduce the theoretical and practical application of triads as (major, minor, dimin­\nished or augmented).\n \nz Introduce the basics of triads-a triad is a three-note chord built from a root, 3rd and \n5th.\n"
    },
    {
      "page": 29,
      "text": "Form 1 Term 2\nTeaching Module\n21\n \nz Guide learners how to identify intervals in a triad e.g. Major 3rd which has 3 steps \nwith 4 semitones – (C to E) and minor 3rd has 3 steps with 3 semitones (C to E \nflat…)\n \nz Major triad –structure is root +major third +perfect fifth\n \nz Minor triad structure has root + minor third + perfect.\nActivity 4: Inverting triads.\nTeaching inverting triads involves a structured approach that helps learners understand the con­\ncept of triads, their inversions and how to identify and perform them.\nTask 1: Invert triads from root position to first and second inversion.\nTIPS\n \nz Guide learners on how to invert triads from root, first and second inversion.\n \nz Provide worksheets where learners must label triads and their inversions in musical \nnotation.\n \nz Have learners practice performing triads and their inversions on their instruments.\n \nz Start with simple major and minor triads before moving to diminished and augmented.\nActivity 5: Playing triads.\nTask 1: Perform each type of triad (Major, minor, diminished and augmented) on an instrument \n(piano, guitar…)\nTIPS\n \nz Guide learners how to play triads on an instrument\n \nz Give learners a root note and have them play the third and the fifth notes.\n \nz Engage learners in ear training by identifying the played triads (Major, minor...)\n \nz Comparative listening-guide: learners to play in pairs e.g. major vs minor and have \nstudents describe emotional quality of each.\nSpecific competence: 1.8.1.2 Apply primary and secondary triads\nSuggested Methodology: Discussion, Demonstration, individual…\nLearning environment setup: Any environment such as, (any outdoor), artificial (music \nroom…) and technological (video…).\nSuggested Teaching and Learning Materials: Piano, keyboard, guitars, charts…\nLEARNING ACTIVITIES\nActivity 1: Identifying primary and secondary triads in any given scale.\n"
    },
    {
      "page": 30,
      "text": "Musical Arts Education\nTeaching Module\n22\nTask 1: Learners to identify primary and secondary triads in groups in any given scale.\nTIP\n Carefully guide learners how to identify primary and secondary triads in any given scale.\nActivity 2: Applying primary and secondary triads in any given scale.\nTask 1: Learners construct primary and secondary triads in any given scale/key.\nTIP\n \nz Guide learners how to construct primary and secondary triads in any given key/\nscale.\nExpected standard: Primary and secondary triads in any given scale applied correctly.\nASSESSMENT CRITERIA\nPrepare tasks to be administered during and after learning sessions and give carry home tasks.\n \nz Create a quiz to test learners’ ability to understand primary and secondary triads in \nany given key/scale.\n \nz Assign a project where learners analyse and identify primary and secondary triads in \nany given key/scale.\n \nz Ask learners to create and notate simple chord progressions of primary and secondary \ntriads in any given key/scale.\nSUMMARY\n This topic has highlighted the following:\n \nz Harmony refers to the combination of different musical notes played or sung at the \nsame time to produce a pleasing sound.\n \nz A triad is a three-note chord built from a root, third and fifth. It is a group of three \nnotes played or sung simultaneously. \n      When we refer to the root, third and fifth, we mean that:\n \nz The root is a base note (foundation note).\n \nz The third is a third interval above the root.\n \nz The fifth is a fifth note (a perfect 5th) above the root.\n"
    },
    {
      "page": 31,
      "text": "Form 1 Term 2\nTeaching Module\n23\n                                                     BIBLIOGRAPHY\nBenson Abwao and David Nyachieo (1995) PTE Revision Series Music for Primary Teachers \nEducation. Printing Services Kenya. \nHafman,Miles (1997) Syncopation: National Symphony Orccestra; Retrieved (2009) Ministry of \nEducation (2023) Zambia Education Curriculum Framework, Curriculum Development Centre \nLusaka, Zambia. \nMinisty of Education (2024) Music Art Education Ordinary Secondary Level Form 1 -4 Syllabus, \nCurriculum Development Centre Lusaka: Zambia. \nMinistry of Education (2023). Zambia Education Curriculum Framework. Lusaka: Zambia \nSnoman, Rick (2004). Dance Music Manual: toys, tools and techniques,\n"
    },
    {
      "page": 32,
      "text": "Musical Arts Education\nTeaching Module\n24\n Appendix: SAMPLE LESSON PLAN TEMPLATE \nSCHOOL: _________________________________________________________________\nNAME OF TEACHER: __________________________           DATE: ________________\nCLASS: ______________\t\n\t\n\t\n\t\nDURATION: _________________\nTOTAL ENROLLMENT: BOYS _____GIRLS_______           TIME: ____________  \nTOTAL ATTENDANCE: BOYS _____GIRLS_______                                                                     \nSUBJECT: _____________________________________\t \t\n\t\n\t\nTOPIC: __________________ (This must come from the syllabus with its serial number)\t\nSUB-TOPIC: ___________\t (This must come from the syllabus with its serial number)\t\nGENERAL COMPETENCES: _________________________________________________\n____________________________________________________________________________\nSPECIFIC COMPETENCES: _______________________ (This must come from the syllabus \nwith its serial number)\t\nRATIONALE: _______________________________________________________________\n____________________________________________________________________________\n____________________________________________________________________________\nPRIOR KNOWLEDGE: ______________________________________________________\n____________________________________________________________________________\nREFERENCES: _____________________________________________________________\n____________________________________________________________________________\n____________________________________________________________________________\nLEARNING ENVIRONMENT \nNatural environment: _________________________________________________________\nArtificial environment: ________________________________________________________\nTechnological environment: ____________________________________________________\nTEACHING AND LEARNING MATERIALS/RESOURCES: _______________________\nEXPECTED STANDARD:_____________________________________________________\n(This must come from the syllabus as it is)\t\n"
    },
    {
      "page": 33,
      "text": "Form 1 Term 2\nTeaching Module\n25\nLESSON PROGRESSION:\nSTAGES\nTEACHER’S \nACTIVITIES\nLEARNERS’ \nACTIVITIES\nASSESSMENT \nCRITERIA\nINTRODUCTION\n5 Minutes\nLESSON \nDEVELOP­\nMENT\n5 Minutes\n15 Minutes\n15 Minutes\nEXERCISE \n/APPLICA­\nTION\n20 Minutes\n \nCONCLUSION\n10 Minutes\nHOMEWORK: ______________________________________________________________\n____________________________________________________________________________\n____________________________________________________________________________\nLESSON EVALUATION:\n____________________________________________________________________________\n"
    },
    {
      "page": 34,
      "text": "Musical Arts Education\nTeaching Module\n26\nAppendix: SAMPLE LESSON PLAN\nSCHOOL: BROADWAY SECONDARY \nNAME OF TEACHER: TINA KAPAMPA CHINYAMA                 DATE: 18TH APRIL, 2025\nCLASS: FORM 1 M\t \t\n\t\n\t\n\t\n             DURATION: 80 MINUTES\nTOTAL ENROLLMENT: BOYS: 25 GIRLS: 30          TIME:07: 30 HOURS- 08:50 HOURS \nTOTAL ATTENDANCE: BOYS: 25 GIRLS:  30                                                                     \nSUBJECT: MUSICAL ARTS EDUCATION\t\n\t\n\t\n\t\nTOPIC: 1.8 HARMONY   \t\nSUB-TOPIC: TRIADS\t\nGENERAL COMPETENCES: Analytical thinking, Collaboration, Creativity and Innovation, \nCritical thinking, Digital thinking and Problem solving.\nSPECIFIC COMPETENCES: 1.8.1.1 Construct triads\nRATIONALE: This lesson will focus on constructing triads which is a fundamental skill in \nmusic theory, designed to help learners recognise and appreciate harmony in music. In this \nlesson, learners will acquire a skill in constructing triads through demonstration, discussion, and \ngroup work and think pair. Understanding how to build triads, empowers learners to create their \nown music and apply harmony in a real life situation. This lesson is lesson 1 in a series of 7.\nPRIOR KNOWLEDGE: Pitch, Intervals and Melody (basic music notation, scale knowledge \nstaff notation, note reading, note names and positions, basic chord concept, note values and rests)\nREFERENCES: \n \nz 2025 Musical Arts Education Form 1- Teaching Module page 33.\n \nz Harmony theory- James e. Perone page 55.\n \nz WWW.youtube video on Triads.\nLEARNING ENVIRONMENT \nNatural environment: (any outdoor)\nArtificial environment/ Technological environment: (music room…) and technological \n(video…)\nTEACHING AND LEARNING MATERIALS/RESOURCES: Piano, keyboard, guitars, \ncharts…\nEXPECTED STANDARD: Triads constructed correctly. (It will only be exhausted upon \ncompletion of all the lined up activities)\n(This must come from the syllabus as it is)\n"
    },
    {
      "page": 35,
      "text": "Form 1 Term 2\nTeaching Module\n27\nLESSON PROGRESSION\nSTAGES\nTEACHER’S ACTIVITIES\nLEARNERS’ \nACTIVITIES\nASSESSMENT \nCRITERIA\nINTRODUC­\nTION      5 \nMinutes\n \nz Divide learners into three \ngroups and assign sol-fa \nsyllables to each group \n(Do, Mi and So).  Ask \nthem to build the 3rd and \n5th on each sol-fa respec­\ntively. \n \nz Explain what a triad is \n(refer to notes in the \nModule and other pre­\npared notes)\n \nz Build the 3rd \nand 5th to the \nassigned sol-fa \nsyllables. \n \nz Observe learner \nengagement and \nparticipation \nL E S S O N \nDEVELOP­\nMENT\n10 Minutes\n \nz Discuss with learners \nhow to identify a triad.\nActivity 1\nAsk learners to \nidentify and label \nthe triads as root, \nthird and fifth on a \nstaff using the tonic \ntriad in C major.\n \nz Assess understand­\ning of a Triad.\n \nz Assess \nlearners’ \nability to identify \nand label the triads \nas root, third and \nfifth on a staff using \nthe tonic triad in C \nmajor.\n15 Minutes\n \nz Demonstrate with learn­\ners how to construct a \ntriad (root, 3rd and 5th \npositions) on the staff, \nand on the keyboard.  \nActivity 2\nConstructing triads, \n(root, 3rd, 5th)\n \nz Evaluate the learn­\ner’s ability to con­\nstruct triads (root, \n3rd and 5th positions) \nfocussing on: \n \nz Accuracy of con­\nstructing a triad.\n \nz Understanding the \nformation of triads \nand their character­\nistics.\n"
    },
    {
      "page": 36,
      "text": "Musical Arts Education\nTeaching Module\n28\nEXERCISE \n/APPLICA­\nTION\n20 Minutes\n \nz Ask learners to identify \nand label the triads as \nroot, third and fifth on a \nstaff.\nTask 1: \n \nz Identifying and \nlabelling the \ntriads as root, \nthird and fifth \non a staff using \nthe tonic triad \nin C major.\n \nz Assess learners’ \nability to identify \nand label the triads \nas root, third and \nfifth on a staff.\n20 Minutes\n \nz Engage learners in con­\nstructing triads (root, 3rd, \n5th) on the staff in differ­\nent keys.\nTask 2:\nconstruct triads in \n(root, 3rd, 5th) on \nthe staff in different \nkeys.\n \nAssess learner’s ability \nto construct triads in \n(root, 3rd, 5th) on the \nstaff in different keys,\nfocussing on: \n \nz Exploration of \ndifferent scale \ndegrees.\n \nz Creativity in con­\nstruction\nC O N C L U ­\nSION\n10 Minutes\nReview key concepts:\n \nz What a triad is.\n \nz Identification of triads.\n \nz Learners reflect on what \nthey learnt on construc­\ntion of triads.\nSharing reflections \nand insights on:\n \nz What a triad is.\n \nz Identification of \ntriads.\n \nz Learners re­\nflect on what \nthey learnt on \nconstruction of \ntriads.\nEvaluate learners’ \nunderstanding of what a \ntriad is, identification of \ntriads and constructing \nof triads.\n \nz Suggest areas of \nimprovement.\nHOMEWORK: Learners to construct triads in (root, 3rd, 5th) on the staff in G major.\n"
    },
    {
      "page": 37,
      "text": "Form 1 Term 2\nTeaching Module\n29\nLESSON EVALUATION:\nLearners were able to construct triads in root, 3rd and 5th positions by applying critical and \nanalytical thinking in identifying different triads. However, five learners experienced difficulty \nin reading staff notation which slowed down triad construction. There is need to revisit basic note \nreading and intervals in the next lesson to reinforce foundation. \n"
    }
  ],
  "needs_manual_review": false
}
